<?xml version="1.0" encoding="UTF-8"?>
<form xmlns:xsi="http://www.w3.org/2001/XMLSchema-instance" xsi:noNamespaceSchemaLocation="urn:magento:module:Magento_Ui:etc/ui_configuration.xsd">
    <argument name="data" xsi:type="array">
        <item name="js_config" xsi:type="array">
            <item name="provider" xsi:type="string">bannerslider_form.bannerslider_form_data_source</item>
            <item name="deps" xsi:type="string">bannerslider_form.bannerslider_form_data_source</item>
        </item>
        <item name="label" xsi:type="string" translate="true">General Information</item>
        <item name="config" xsi:type="array">
            <item name="dataScope" xsi:type="string">data</item>
            <item name="namespace" xsi:type="string">bannerslider_form</item>
        </item>
        <item name="spinner" xsi:type="string">general_information</item>
        <item name="buttons" xsi:type="array">
            <item name="back" xsi:type="string">ET\Bannerslider\Block\Adminhtml\Index\Edit\Button\Back</item>
            <item name="delete" xsi:type="string">ET\Bannerslider\Block\Adminhtml\Index\Edit\Button\Delete</item>
            <item name="reset" xsi:type="string">ET\Bannerslider\Block\Adminhtml\Index\Edit\Button\Reset</item>
            <item name="save" xsi:type="string">ET\Bannerslider\Block\Adminhtml\Index\Edit\Button\Save</item>
        </item>
        <item name="template" xsi:type="string">templates/form/collapsible</item>
    </argument>
    <dataSource name="bannerslider_form_data_source">
        <argument name="dataProvider" xsi:type="configurableObject">
            <argument name="class" xsi:type="string">ET\Bannerslider\Model\DataProvider</argument>
            <argument name="name" xsi:type="string">bannerslider_form_data_source</argument>
            <argument name="primaryFieldName" xsi:type="string">id</argument>
            <argument name="requestFieldName" xsi:type="string">id</argument>
            <argument name="data" xsi:type="array">
                <item name="config" xsi:type="array">
                    <item name="submit_url" xsi:type="url" path="*/*/save" />
                </item>
            </argument>
        </argument>
        <argument name="data" xsi:type="array">
            <item name="js_config" xsi:type="array">
                <item name="component" xsi:type="string">Magento_Ui/js/form/provider</item>
            </item>
        </argument>
    </dataSource>
    <fieldset name="general_information">
        <argument name="data" xsi:type="array">
            <item name="config" xsi:type="array">
                <item name="collapsible" xsi:type="boolean">false</item>
                <item name="label" xsi:type="string" translate="true">General Information</item>
                <item name="sortOrder" xsi:type="number">20</item>
            </item>
        </argument>
        <field name="status">
            <argument name="data" xsi:type="array">
                <item name="config" xsi:type="array">
                    <item name="sortOrder" xsi:type="number">10</item>
                    <item name="dataType" xsi:type="string">boolean</item>
                    <item name="formElement" xsi:type="string">checkbox</item>
                    <item name="prefer" xsi:type="string">toggle</item>
                    <item name="label" xsi:type="string" translate="true">Status</item>
                    <item name="valueMap" xsi:type="array">
                        <item name="true" xsi:type="number">1</item>
                        <item name="false" xsi:type="number">0</item>
                    </item>
                    <item name="valuesForOptions" xsi:type="array">
                        <item name="boolean" xsi:type="string">boolean</item>
                    </item>
                    <item name="default" xsi:type="number">1</item>
                    <item name="dataScope" xsi:type="string">status</item>
                </item>
            </argument>
        </field>
        <field name="name">
            <argument name="data" xsi:type="array">
                <item name="config" xsi:type="array">
                    <item name="dataType" xsi:type="string">text</item>
                    <item name="label" xsi:type="string" translate="true">Title</item>
                    <item name="formElement" xsi:type="string">input</item>
                    <item name="source" xsi:type="string">name</item>
                    <item name="dataScope" xsi:type="string">name</item>
                </item>
            </argument>
        </field>
        <field formElement="imageUploader" name="img">
            <argument name="data" xsi:type="array">
                <item name="config" xsi:type="array">
                    <item name="source" xsi:type="string">block</item>
                </item>
            </argument>
            <settings>
                <elementTmpl>ui/form/element/uploader/image</elementTmpl>
                <dataType>string</dataType>
                <label translate="true">Image</label>
                <visible>true</visible>
                <validation>
                    <rule name="required-entry" xsi:type="boolean">true</rule>
                </validation>
            </settings>
            <formElements>
                <imageUploader>
                    <settings>
                        <required>true</required>
                        <uploaderConfig>
                            <param xsi:type="url" name="url" path="bannerslider/index/uploader"/>
                        </uploaderConfig>
                        <previewTmpl>ET_Bannerslider/image-preview</previewTmpl>
                        <openDialogTitle>Media Gallery</openDialogTitle>
                        <allowedExtensions>jpg jpeg gif png</allowedExtensions>
                        <maxFileSize>4194304</maxFileSize>
                    </settings>
                </imageUploader>
            </formElements>
        </field>
        <field name="link">
            <argument name="data" xsi:type="array">
                <item name="config" xsi:type="array">
                    <item name="dataType" xsi:type="string">text</item>
                    <item name="label" xsi:type="string" translate="true">URL</item>
                    <item name="formElement" xsi:type="string">input</item>
                    <item name="source" xsi:type="string">link</item>
                    <item name="dataScope" xsi:type="string">link</item>
                </item>
            </argument>
        </field>
        <field name="target" formElement="select">
            <argument name="data" xsi:type="array">
                <item name="config" xsi:type="array">
                    <item name="source" xsi:type="string">block</item>
                </item>
            </argument>
            <settings>
                <dataType>int</dataType>
                <label translate="true">URL Target</label>
                <dataScope>target</dataScope>
            </settings>
            <formElements>
                <select>
                    <settings>
                        <options class="ET\Bannerslider\Model\Banner\Source\UrlTarget"/>
                    </settings>
                </select>
            </formElements>
        </field>
        <field name="start_date" formElement="date">
            <argument name="data" xsi:type="array">
                <item name="config" xsi:type="array">
                    <item name="source" xsi:type="string">block</item>
                </item>
            </argument>
            <settings>
                <validation>
                    <rule name="validate-date" xsi:type="boolean">true</rule>
                </validation>
                <dataType>text</dataType>
                <label translate="true">Start Date</label>
                <dataScope>start_date</dataScope>
            </settings>
        </field>
        <field name="end_date" formElement="date">
            <argument name="data" xsi:type="array">
                <item name="config" xsi:type="array">
                    <item name="source" xsi:type="string">page</item>
                </item>
            </argument>
            <settings>
                <validation>
                    <rule name="validate-date" xsi:type="boolean">true</rule>
                </validation>
                <dataType>text</dataType>
                <label translate="true">End Date</label>
                <dataScope>end_date</dataScope>
            </settings>
        </field>
        <field name="storeviews" formElement="multiselect">
            <argument name="data" xsi:type="array">
                <item name="config" xsi:type="array">
                    <item name="source" xsi:type="string">block</item>
                    <item name="default" xsi:type="number">0</item>
                </item>
            </argument>
            <settings>
                <validation>
                    <rule name="required-entry" xsi:type="boolean">true</rule>
                </validation>
                <dataType>int</dataType>
                <label translate="true">Store View</label>
                <dataScope>store_id</dataScope>
            </settings>
            <formElements>
                <multiselect>
                    <settings>
                        <options class="ET\Bannerslider\Ui\Component\Listing\Column\Banner\Options"/>
                    </settings>
                </multiselect>
            </formElements>
        </field>
        <field name="disable_mobile">
            <argument name="data" xsi:type="array">
                <item name="config" xsi:type="array">
                    <item name="dataType" xsi:type="string">boolean</item>
                    <item name="formElement" xsi:type="string">checkbox</item>
                    <item name="prefer" xsi:type="string">toggle</item>
                    <item name="label" xsi:type="string" translate="true">Disable For Mobile</item>
                    <item name="valueMap" xsi:type="array">
                        <item name="true" xsi:type="number">1</item>
                        <item name="false" xsi:type="number">0</item>
                    </item>
                    <item name="valuesForOptions" xsi:type="array">
                        <item name="boolean" xsi:type="string">boolean</item>
                    </item>
                    <item name="default" xsi:type="number">0</item>
                    <item name="dataScope" xsi:type="string">disable_mobile</item>
                </item>
            </argument>
        </field>
        <field name="sort_order">
            <argument name="data" xsi:type="array">
                <item name="config" xsi:type="array">
                    <item name="dataType" xsi:type="string">text</item>
                    <item name="label" xsi:type="string" translate="true">Sort Order</item>
                    <item name="formElement" xsi:type="string">input</item>
                    <item name="source" xsi:type="string">sort_order</item>
                    <item name="dataScope" xsi:type="string">sort_order</item>
                </item>
            </argument>
        </field>
    </fieldset>
    <fieldset name="content_information">
        <argument name="data" xsi:type="array">
            <item name="config" xsi:type="array">
                <item name="collapsible" xsi:type="boolean">true</item>
                <item name="label" xsi:type="string" translate="true">Content Information</item>
                <item name="sortOrder" xsi:type="number">30</item>
            </item>
        </argument>
        <field name="content_position" formElement="select">
            <argument name="data" xsi:type="array">
                <item name="config" xsi:type="array">
                    <item name="source" xsi:type="string">block</item>
                </item>
            </argument>
            <settings>
                <dataType>int</dataType>
                <label translate="true">Content Position</label>
                <dataScope>content_position</dataScope>
            </settings>
            <formElements>
                <select>
                    <settings>
                        <options class="ET\Bannerslider\Model\Banner\Source\ContentPosition"/>
                    </settings>
                </select>
            </formElements>
        </field>
        <field name="content">
            <argument name="data" xsi:type="array">
                <item name="config" xsi:type="array">
                    <item name="label" xsi:type="string" translate="true">Banner Content</item>
                    <item name="formElement" xsi:type="string">wysiwyg</item>
                    <item name="template" xsi:type="string">ui/form/field</item>
                    <item name="wysiwyg" xsi:type="boolean">true</item>
                    <item name="visible" xsi:type="boolean">true</item>
                    <item name="dataType" xsi:type="string">text</item>
                </item>
            </argument>
        </field>
    </fieldset>
</form>